gogoanime/__init__.py
gogoanime/__main__.py
gogoanimepy-0.0.3.dist-info/LICENSE
gogoanimepy-0.0.3.dist-info/METADATA
gogoanimepy-0.0.3.dist-info/WHEEL
gogoanimepy-0.0.3.dist-info/top_level.txt
gogoanimepy-0.0.3.dist-info/RECORD
