Metadata-Version: 2.1
Name: gogoanimepy
Version: 0.0.3
Summary: Gogoanime webscrapper
Home-page: https://github.com/vichubenzene/gogoanimepy
Author: Viswanathan
Author-email: vichusathappan@example.com
Project-URL: Bug Tracker, https://github.com/vichubenzene/gogoanimepy/issues
Classifier: Programming Language :: Python :: 3
Classifier: License :: OSI Approved :: MIT License
Classifier: Operating System :: OS Independent
Requires-Python: >=3.6
License-File: LICENSE
